igver/__init__.py
igver/cli.py
igver/igver.py
igver/data/genome_map.yaml
igver-1.1.dist-info/LICENSE
igver-1.1.dist-info/METADATA
igver-1.1.dist-info/WHEEL
igver-1.1.dist-info/entry_points.txt
igver-1.1.dist-info/top_level.txt
igver-1.1.dist-info/RECORD
