Metadata-Version: 2.1
Name: igver
Version: 1.1
Summary: A package to generate IGV screenshots and load them into Matplotlib figures.
Home-page: https://github.com/shahcompbio/igver
Author: Seongmin Choi
Author-email: soymintc@gmail.com
Classifier: Programming Language :: Python :: 3
Classifier: License :: OSI Approved :: MIT License
Classifier: Operating System :: OS Independent
Requires-Python: >=3.6
License-File: LICENSE
Requires-Dist: matplotlib
Requires-Dist: Pillow
Requires-Dist: subprocess32 ; python_version < "3.5"
Requires-Dist: importlib-resources ; python_version < "3.9"
